ChitraPy/__init__.py
ChitraPy/filters.py
ChitraPy/helpers.py
tests/__init__.py
tests/tests.py
ChitraPy-0.0.3.dist-info/LICENSE
ChitraPy-0.0.3.dist-info/METADATA
ChitraPy-0.0.3.dist-info/WHEEL
ChitraPy-0.0.3.dist-info/top_level.txt
ChitraPy-0.0.3.dist-info/zip-safe
ChitraPy-0.0.3.dist-info/RECORD
