Metadata-Version: 2.1
Name: ChitraPy
Version: 0.0.3
Summary: Digital Image Processing Library.
Home-page: https://github.com/mgautam98/ChitraPy
Author: Gautam Mishra
Author-email: mishragautam96@gmail.com
License: GNU General Public License v3 (GPLv3)
Platform: UNKNOWN
Classifier: Programming Language :: Python :: 3
Classifier: License :: OSI Approved :: GNU General Public License v3 (GPLv3)
Classifier: Operating System :: OS Independent
Requires-Dist: numpy
Requires-Dist: matplotlib
Requires-Dist: numba
